django_budget/__init__.py
django_budget/base/__init__.py
django_budget/base/forms.py
django_budget/base/models.py
django_budget/base/templatetags/__init__.py
django_budget/base/templatetags/active_tags.py
django_budget/base/templatetags/budget_tags.py
django_budget/base/tests/__init__.py
django_budget/base/tests/tests_tags.py
django_budget/base/tests/tests_views.py
django_budget/base/utils.py
django_budget/base/views.py
django_budget/budget/__init__.py
django_budget/budget/admin.py
django_budget/budget/forms.py
django_budget/budget/migrations/__init__.py
django_budget/budget/models.py
django_budget/budget/templates/budget/add.html
django_budget/budget/templates/budget/delete.html
django_budget/budget/templates/budget/edit.html
django_budget/budget/templates/budget/list.html
django_budget/budget/templates/estimate/add.html
django_budget/budget/templates/estimate/delete.html
django_budget/budget/templates/estimate/edit.html
django_budget/budget/templates/estimate/list.html
django_budget/budget/tests/__init__.py
django_budget/budget/tests/tests_budget_models.py
django_budget/budget/tests/tests_budget_views.py
django_budget/budget/tests/tests_estimate_models.py
django_budget/budget/tests/tests_estimate_views.py
django_budget/budget/tests/tests_forms.py
django_budget/budget/urls.py
django_budget/budget/views.py
django_budget/category/__init__.py
django_budget/category/admin.py
django_budget/category/forms.py
django_budget/category/migrations/__init__.py
django_budget/category/models.py
django_budget/category/templates/category/add.html
django_budget/category/templates/category/delete.html
django_budget/category/templates/category/edit.html
django_budget/category/templates/category/list.html
django_budget/category/tests/__init__.py
django_budget/category/tests/tests_forms.py
django_budget/category/tests/tests_models.py
django_budget/category/tests/tests_views.py
django_budget/category/urls.py
django_budget/category/views.py
django_budget/dashboard/__init__.py
django_personal_finance-0.0.2.dist-info/LICENSE.txt
django_personal_finance-0.0.2.dist-info/METADATA
django_personal_finance-0.0.2.dist-info/WHEEL
django_personal_finance-0.0.2.dist-info/entry_points.txt
django_personal_finance-0.0.2.dist-info/RECORD
